pykkt/__init__.py
pykkt/client.py
pykkt/connections.py
pykkt/constants.py
pykkt/exceptions.py
pykkt/utils.py
pykkt-0.1.0.dist-info/LICENSE
pykkt-0.1.0.dist-info/METADATA
pykkt-0.1.0.dist-info/WHEEL
pykkt-0.1.0.dist-info/RECORD
