Metadata-Version: 2.3
Name: pykkt
Version: 0.1.0
Summary: 
Author: white
Author-email: sasha.2000ibr@gmail.com
Requires-Python: >=3.9,<4.0
Classifier: Programming Language :: Python :: 3
Classifier: Programming Language :: Python :: 3.9
Classifier: Programming Language :: Python :: 3.10
Classifier: Programming Language :: Python :: 3.11
Classifier: Programming Language :: Python :: 3.12
Classifier: Programming Language :: Python :: 3.13
Requires-Dist: aioserial (>=1.3.1,<2.0.0)
Requires-Dist: pyserial (>=3.5,<4.0)
